MANIFEST.in
README.rst
setup.py
docs/_build/html/.buildinfo
docs/_build/html/genindex.html
docs/_build/html/index.html
docs/_build/html/objects.inv
docs/_build/html/py-modindex.html
docs/_build/html/search.html
docs/_build/html/searchindex.js
docs/_build/html/_sources/index.txt
docs/_build/html/_sources/modules/query.txt
docs/_build/html/_sources/modules/rest_function.txt
docs/_build/html/_sources/modules/routers.txt
docs/_build/html/_sources/modules/serializers.txt
docs/_build/html/_sources/modules/serve.txt
docs/_build/html/_sources/modules/views.txt
docs/_build/html/_static/ajax-loader.gif
docs/_build/html/_static/alabaster.css
docs/_build/html/_static/basic.css
docs/_build/html/_static/classic.css
docs/_build/html/_static/comment-bright.png
docs/_build/html/_static/comment-close.png
docs/_build/html/_static/comment.png
docs/_build/html/_static/doctools.js
docs/_build/html/_static/down-pressed.png
docs/_build/html/_static/down.png
docs/_build/html/_static/file.png
docs/_build/html/_static/jquery-1.11.1.js
docs/_build/html/_static/jquery.js
docs/_build/html/_static/minus.png
docs/_build/html/_static/plus.png
docs/_build/html/_static/pygments.css
docs/_build/html/_static/searchtools.js
docs/_build/html/_static/sidebar.js
docs/_build/html/_static/underscore-1.3.1.js
docs/_build/html/_static/underscore.js
docs/_build/html/_static/up-pressed.png
docs/_build/html/_static/up.png
docs/_build/html/_static/websupport.js
docs/_build/html/modules/query.html
docs/_build/html/modules/rest_function.html
docs/_build/html/modules/routers.html
docs/_build/html/modules/serializers.html
docs/_build/html/modules/serve.html
docs/_build/html/modules/views.html
pumpwood_flaskmisc/__init__.py
pumpwood_flaskmisc/database.py
pumpwood_flaskmisc/models.py
pumpwood_flaskmisc/query.py
pumpwood_flaskmisc/testing.py
pumpwood_flaskmisc.egg-info/PKG-INFO
pumpwood_flaskmisc.egg-info/SOURCES.txt
pumpwood_flaskmisc.egg-info/dependency_links.txt
pumpwood_flaskmisc.egg-info/requires.txt
pumpwood_flaskmisc.egg-info/top_level.txt