Metadata-Version: 1.0
Name: pumpwood-flaskmisc
Version: 0.0.0.1
Summary: Misceletiuns fucntions and class to help development of PumpWood on Flash
Home-page: UNKNOWN
Author: André Andrade Baceti
Author-email: a.baceti@murabei.com
License: UNKNOWN
Platform: UNKNOWN
